<?xml version="1.0" encoding="UTF-8"?>
<metadata xml:lang="en"><Esri><CreaDate>20230618</CreaDate><CreaTime>18023600</CreaTime><ArcGISFormat>1.0</ArcGISFormat><SyncOnce>TRUE</SyncOnce><DataProperties><lineage><Process ToolSource="c:\program files (x86)\arcgis\desktop10.2\ArcToolbox\Toolboxes\Arc Hydro Tools.tbx\AssignHydroID" Date="20230618" Time="180103">AssignHydroID C:\Users\VVS\AppData\Local\Temp\arc6931\untitled.gdb\Layers\LongestFlowPathCat OVERWRITE_NO</Process></lineage></DataProperties></Esri></metadata>
